fastim/__init__.py
fastim/import.py
fastim-0.0.4.dist-info/LICENSE
fastim-0.0.4.dist-info/METADATA
fastim-0.0.4.dist-info/WHEEL
fastim-0.0.4.dist-info/top_level.txt
fastim-0.0.4.dist-info/RECORD
